aiosplunk/__init__.py
aiosplunk/client.py
aiosplunk/exceptions.py
aiosplunk/search.py
aiosplunk-0.3.1.dist-info/METADATA
aiosplunk-0.3.1.dist-info/WHEEL
aiosplunk-0.3.1.dist-info/licenses/LICENSE
aiosplunk-0.3.1.dist-info/RECORD
