Metadata-Version: 2.4
Name: aiosplunk
Version: 0.3.1
Summary: Async Splunk SDK
License: MIT
License-File: LICENSE
Requires-Python: >=3.11
Requires-Dist: httpx
